treepathmap/__init__.py
treepathmap/maps.py
treepathmap/selectables.py
treepathmap/selections.py
treepathmap/treepaths.py
treepathmap-0.2a2.dist-info/LICENSE.md
treepathmap-0.2a2.dist-info/METADATA
treepathmap-0.2a2.dist-info/WHEEL
treepathmap-0.2a2.dist-info/top_level.txt
treepathmap-0.2a2.dist-info/RECORD
