Metadata-Version: 2.1
Name: treepathmap
Version: 0.2a2
Summary: Providing navigation and selection within nested collections.
Home-page: https://gitlab.com/david.scheliga/treepathmap
Author: David Scheliga
License: GNU General Public License V3 (GPLv3)
Project-URL: Documentation, https://treepathmap.readthedocs.io/en/latest/
Project-URL: Source Code Repository, https://gitlab.com/david.scheliga/treepathmap
Keywords: doctest,helper,pandas
Platform: UNKNOWN
Classifier: Development Status :: 3 - Alpha
Classifier: License :: OSI Approved :: GNU General Public License v3 (GPLv3)
Classifier: Operating System :: OS Independent
Classifier: Programming Language :: Python
Classifier: Programming Language :: Python :: 3.6
Classifier: Programming Language :: Python :: 3.7
Classifier: Programming Language :: Python :: 3.8
Classifier: Programming Language :: Python :: 3.9
Requires-Dist: pandas (>=1.0.0)
Requires-Dist: numpy (>=1.16.0)
Requires-Dist: treenodedefinition
